{
	"_type": "spritesheets",
	"spritesheets": {
		"entity": {
			"_type": "spritesheet",
			"_meta": {
				"image": "0",
				"defaultWidth": 24,
				"defaultHeight": 10
			},
			"arrow": {
				"10": {
					"x": 0,
					"y": 0,
					"w": 40,
					"h": 43
				},
				"11": {
					"x": 0,
					"y": 43,
					"w": 40,
					"h": 43
				},
				"_folder": true,
				"-1-1": {
					"x": 40,
					"y": 0,
					"w": 40,
					"h": 43
				},
				"-10": {
					"x": 40,
					"y": 43,
					"w": 40,
					"h": 43
				},
				"-11": {
					"x": 80,
					"y": 0,
					"w": 40,
					"h": 43
				},
				"0-1": {
					"x": 80,
					"y": 43,
					"w": 40,
					"h": 43
				},
				"01": {
					"x": 120,
					"y": 0,
					"w": 40,
					"h": 43
				},
				"1-1": {
					"x": 120,
					"y": 43,
					"w": 40,
					"h": 43
				}
			},
			"banana": {
				"_folder": true,
				"fly0": {
					"x": 332,
					"y": 24,
					"w": 10
				},
				"fly1": {
					"x": 332,
					"y": 34,
					"w": 10
				},
				"fly2": {
					"x": 332,
					"y": 44,
					"w": 10
				},
				"fly3": {
					"x": 16,
					"y": 86,
					"w": 10
				},
				"idle": {
					"x": 26,
					"y": 86,
					"w": 10
				}
			},
			"bat": {
				"_folder": true,
				"fly0": {
					"x": 296,
					"y": 56,
					"w": 22,
					"h": 15
				},
				"fly1": {
					"x": 296,
					"y": 71,
					"w": 22,
					"h": 15
				},
				"fly2": {
					"x": 304,
					"y": 0,
					"w": 22,
					"h": 15
				},
				"hang0": {
					"x": 338,
					"y": 0,
					"w": 8,
					"h": 11
				},
				"hang1": {
					"x": 318,
					"y": 56,
					"w": 22,
					"h": 15
				}
			},
			"chainedBall": {
				"_folder": true,
				"ball0": {
					"x": 36,
					"y": 86,
					"w": 10
				},
				"ball1": {
					"x": 46,
					"y": 86,
					"w": 10
				},
				"chain": {
					"x": 320,
					"y": 51,
					"w": 5,
					"h": 5
				},
				"particle0": {
					"x": 348,
					"y": 54,
					"w": 8,
					"h": 8
				},
				"particle1": {
					"x": 350,
					"y": 21,
					"w": 8,
					"h": 8
				},
				"particle2": {
					"x": 350,
					"y": 29,
					"w": 8,
					"h": 8
				}
			},
			"doors": {
				"_folder": true,
				"entry1": {
					"x": 224,
					"y": 80,
					"h": 16
				},
				"entry2": {
					"x": 248,
					"y": 80,
					"h": 16
				},
				"exit1": {
					"x": 296,
					"y": 24,
					"h": 16
				},
				"exit2": {
					"x": 296,
					"y": 40,
					"h": 16
				}
			},
			"explosion": {
				"_folder": true,
				"frame0": {
					"x": 224,
					"y": 32,
					"h": 24
				},
				"frame1": {
					"x": 224,
					"y": 56,
					"h": 24
				},
				"frame2": {
					"x": 248,
					"y": 32,
					"h": 24
				},
				"frame3": {
					"x": 248,
					"y": 56,
					"h": 24
				},
				"frame4": {
					"x": 256,
					"y": 0,
					"h": 24
				},
				"frame5": {
					"x": 272,
					"y": 24,
					"h": 24
				},
				"frame6": {
					"x": 272,
					"y": 48,
					"h": 24
				},
				"frame7": {
					"x": 272,
					"y": 72,
					"h": 24
				},
				"frame8": {
					"x": 280,
					"y": 0,
					"h": 24
				}
			},
			"getFX": {
				"_folder": true,
				"frame0": {
					"x": 160,
					"y": 0,
					"w": 32,
					"h": 32
				},
				"frame1": {
					"x": 160,
					"y": 32,
					"w": 32,
					"h": 32
				},
				"frame2": {
					"x": 160,
					"y": 64,
					"w": 32,
					"h": 32
				},
				"frame3": {
					"x": 192,
					"y": 0,
					"w": 32,
					"h": 32
				},
				"frame4": {
					"x": 192,
					"y": 32,
					"w": 32,
					"h": 32
				},
				"frame5": {
					"x": 192,
					"y": 64,
					"w": 32,
					"h": 32
				},
				"frame6": {
					"x": 224,
					"y": 0,
					"w": 32,
					"h": 32
				}
			},
			"item": {
				"_folder": true,
				"key0": {
					"x": 136,
					"y": 86,
					"w": 8
				},
				"key1": {
					"x": 144,
					"y": 86,
					"w": 8
				},
				"key10": {
					"x": 152,
					"y": 86,
					"w": 8
				},
				"key11": {
					"x": 340,
					"y": 54,
					"w": 8
				},
				"key12": {
					"x": 342,
					"y": 24,
					"w": 8
				},
				"key2": {
					"x": 342,
					"y": 34,
					"w": 8
				},
				"key4": {
					"x": 342,
					"y": 44,
					"w": 8
				},
				"key5": {
					"x": 342,
					"y": 64,
					"w": 8
				},
				"key6": {
					"x": 342,
					"y": 74,
					"w": 8
				},
				"key7": {
					"x": 342,
					"y": 84,
					"w": 8
				},
				"key8": {
					"x": 344,
					"y": 11,
					"w": 8
				},
				"key9": {
					"x": 346,
					"y": 0,
					"w": 8
				},
				"life0": {
					"x": 320,
					"y": 15,
					"w": 12,
					"h": 12
				},
				"life1": {
					"x": 326,
					"y": 0,
					"w": 12,
					"h": 12
				},
				"life2": {
					"x": 320,
					"y": 27,
					"w": 12,
					"h": 12
				},
				"life3": {
					"x": 320,
					"y": 39,
					"w": 12,
					"h": 12
				},
				"life4": {
					"x": 318,
					"y": 71,
					"w": 12,
					"h": 12
				},
				"life5": {
					"x": 318,
					"y": 83,
					"w": 12,
					"h": 12
				},
				"life6": {
					"x": 330,
					"y": 71,
					"w": 12,
					"h": 12
				},
				"life7": {
					"x": 330,
					"y": 83,
					"w": 12,
					"h": 12
				},
				"life8": {
					"x": 332,
					"y": 12,
					"w": 12,
					"h": 12
				}
			},
			"monkey": {
				"_folder": true,
				"hit": {
					"x": 56,
					"y": 86,
					"w": 10
				},
				"idle": {
					"x": 66,
					"y": 86,
					"w": 10
				},
				"jump": {
					"x": 76,
					"y": 86,
					"w": 10
				},
				"run0": {
					"x": 86,
					"y": 86,
					"w": 10
				},
				"run1": {
					"x": 96,
					"y": 86,
					"w": 10
				},
				"run2": {
					"x": 106,
					"y": 86,
					"w": 10
				}
			},
			"spark": {
				"_folder": true,
				"frame0": {
					"x": 116,
					"y": 86,
					"w": 10
				},
				"frame1": {
					"x": 126,
					"y": 86,
					"w": 10
				}
			},
			"worm": {
				"_folder": true,
				"walk0": {
					"x": 256,
					"y": 24,
					"w": 16,
					"h": 8
				},
				"walk1": {
					"x": 304,
					"y": 15,
					"w": 16,
					"h": 8
				},
				"walk2": {
					"x": 296,
					"y": 86,
					"w": 16,
					"h": 8
				},
				"walk3": {
					"x": 0,
					"y": 86,
					"w": 16,
					"h": 8
				}
			}
		},
		"hud": {
			"_type": "spritesheet",
			"_meta": {
				"image": "1",
				"defaultWidth": 5,
				"defaultHeight": 7
			},
			"cursor": {
				"x": 0,
				"y": 30,
				"w": 8,
				"h": 8
			},
			"healthEmpty": {
				"x": 8,
				"y": 30
			},
			"healthFull": {
				"x": 8,
				"y": 37
			},
			"target": {
				"_folder": true,
				"f0": {
					"x": 0,
					"y": 0,
					"w": 15,
					"h": 15
				},
				"f1": {
					"x": 0,
					"y": 15,
					"w": 15,
					"h": 15
				}
			}
		},
		"icon": {
			"_type": "spritesheet",
			"_meta": {
				"image": "2",
				"defaultWidth": 104,
				"defaultHeight": 16
			},
			"monkey": {
				"x": 0,
				"y": 0,
				"w": 119,
				"h": 35
			},
			"pixelbox": {
				"x": 0,
				"y": 67
			},
			"warp": {
				"x": 0,
				"y": 35,
				"w": 108,
				"h": 32
			}
		},
		"illustrations": {
			"_type": "spritesheet",
			"_meta": {
				"image": "3",
				"defaultWidth": 160,
				"defaultHeight": 144
			},
			"monkeyReunion0": {
				"x": 0,
				"y": 0
			},
			"monkeyReunion1": {
				"x": 0,
				"y": 144
			},
			"monkeyReunion2": {
				"x": 0,
				"y": 288
			},
			"monkeyStorytime0": {
				"x": 0,
				"y": 432
			},
			"monkeyStorytime1": {
				"x": 0,
				"y": 576
			},
			"monkeyStorytime2": {
				"x": 0,
				"y": 720
			}
		}
	}
}